{
    "taxonLatname": "Notocomplana erythrotaenia",
    "taxonAuthor": "(Schmarda, 1859)",
    "taxonSource": "taxonomy.sources.col",
    "nameUuid": "df8fea33-1e2e-4d39-a7a2-36a48d2c9b96",
    "taxonNuid": "00100s012009001008006001004",
    "gbifNubkey": 6479632,
    "image": {
        "text": "",
        "altText": "",
        "title": "",
        "imageUrl": {
            "1x": "/localcosmos/user_content/content_images/image-1752-250.webp",
            "2x": "/localcosmos/user_content/content_images/image-1752-500.webp",
            "4x": "/localcosmos/user_content/content_images/image-1752-1000.webp"
        }
    },
    "shortProfile": null,
    "taxonProfileId": 137,
    "vernacular": {
        "en": "Limpet flatworm"
    },
    "allVernacularNames": {
        "en": [
            "Limpet flatworm"
        ]
    },
    "nodeNames": [],
    "nodeDecisionRules": [],
    "traits": [],
    "texts": [
        {
            "taxonTextType": "Previous names",
            "shortText": "<p><i>Notoplana patellarum, Polycelis erythrotaenia</i></p>",
            "shortTextKey": "taxon_text_9_1195",
            "longText": null,
            "longTextKey": null,
            "images": []
        },
        {
            "taxonTextType": "Identification features",
            "shortText": "<p>As the name implies flatworms have wide, flat, leaf-like bodies and either glide around on a bed of cilia or, in larger species, by using ripples of muscular contraction that pass along the body.&nbsp; Many tropical species are very brightly-coloured, but those found in the temperate parts of South Africa tend to be more cryptic.</p><p>This species is flat and oval without a frilled margin or any dorsal projections. It is light brown in background colour and marked with a dense network of darker brown spots and patches. It is best identified by its obligate association with large limpets.</p>",
            "shortTextKey": "taxon_text_1_1196",
            "longText": null,
            "longTextKey": null,
            "images": []
        },
        {
            "taxonTextType": "Adult size",
            "shortText": "<p>Typically about 10 mm body length, but can be up to 20 mm.</p>",
            "shortTextKey": "taxon_text_2_1197",
            "longText": null,
            "longTextKey": null,
            "images": []
        },
        {
            "taxonTextType": "Distribution",
            "shortText": "<p><u>Global:</u> The previous <i>Notoplana patellarum</i> was endemic to South Africa, but now that it and several other regional species have been amalgamated under the name <i>Notocomplana erythrotaenia</i>&nbsp; it has become difficult to trace the wider global distribution.</p><p><u>Local/Regional:</u> St Helena Bay to about East London.</p>",
            "shortTextKey": "taxon_text_3_1198",
            "longText": null,
            "longTextKey": null,
            "images": []
        },
        {
            "taxonTextType": "Biology",
            "shortText": "<p>Associated with large limpets, particularly the Goat’s-eye limpet <i>Cymbula oculus</i>. Live in the gill cavity between the foot of the limpet and the shell. There may be several flatworms associated with each individual limpet.&nbsp;</p>",
            "shortTextKey": "taxon_text_4_1199",
            "longText": null,
            "longTextKey": null,
            "images": []
        },
        {
            "taxonTextType": "Food / prey",
            "shortText": "<p>The feeding organ of flatworms is a tubular proboscis on the underside and this leads into a blind-ending gut with no anus. This species is thought to feel on small crustaceans including commensal copepods that are also associated with the host limpets.</p>",
            "shortTextKey": "taxon_text_5_1200",
            "longText": null,
            "longTextKey": null,
            "images": []
        },
        {
            "taxonTextType": "Reproduction",
            "shortText": "<p>Flatworms are hermaphroditic, but cross-fertilise one another by hypodermic impregnation – a process whereby the penis of one individual is stabbed into the partner and sperm injected into the body cavity. The spermatozoa then make their way to the ovaries of the receiving partner. Eggs are laid in gelatinous strings that are often deposited in spiral coils and hatch into free-swimming larvae. These float for a few days in the plankton before settling at new hosts.</p>",
            "shortTextKey": "taxon_text_6_1201",
            "longText": null,
            "longTextKey": null,
            "images": []
        },
        {
            "taxonTextType": "Similar species",
            "shortText": "<p>Fairly easily recognized by its flat speckled-brown body and lack of dorsal tentacles, also by the fact that is found only under limpets.</p>",
            "shortTextKey": "taxon_text_7_1202",
            "longText": null,
            "longTextKey": null,
            "images": []
        },
        {
            "taxonTextType": "Further reading / References",
            "shortText": "Branch, G (1975). The ecology of <i>Patella</i> from the Cape Peninsula, South Africa. 5. Commensalism. <i>Zoologica Africana</i>, 10, 133-162.<br><br>Branch, G, Griffiths, CL, Branch, M & Beckley, L (2016). Two Oceans: A Guide to the Marine Life of Southern Africa. (Fourth edition) Struik Nature, Cape Town. (p. 60)",
            "shortTextKey": "taxon_text_8_1203",
            "longText": null,
            "longTextKey": null,
            "images": []
        }
    ],
    "categorizedTexts": [],
    "images": {
        "primary": {
            "text": "",
            "altText": "",
            "title": "",
            "imageUrl": {
                "1x": "/localcosmos/user_content/content_images/image-1752-250.webp",
                "2x": "/localcosmos/user_content/content_images/image-1752-500.webp",
                "4x": "/localcosmos/user_content/content_images/image-1752-1000.webp"
            }
        },
        "taxonProfileImages": [
            {
                "text": "",
                "altText": "",
                "title": "",
                "imageUrl": {
                    "1x": "/localcosmos/user_content/content_images/image-1752-250.webp",
                    "2x": "/localcosmos/user_content/content_images/image-1752-500.webp",
                    "4x": "/localcosmos/user_content/content_images/image-1752-1000.webp"
                }
            }
        ],
        "nodeImages": [],
        "taxonImages": []
    },
    "synonyms": [
        {
            "taxonLatname": "Leptoplana lyrosora",
            "taxonAuthor": "(Schmarda, 1859)"
        },
        {
            "taxonLatname": "Notoplana erythrotaenia",
            "taxonAuthor": "(Schmarda, 1859)"
        },
        {
            "taxonLatname": "Polycelis erythrotaenia",
            "taxonAuthor": "Schmarda, 1859"
        },
        {
            "taxonLatname": "Polycelis lyrosora",
            "taxonAuthor": "Schmarda, 1859"
        },
        {
            "taxonLatname": "Leptoplana patellarum",
            "taxonAuthor": "Stimpson, 1855"
        },
        {
            "taxonLatname": "Leptoplana erythrotaenia",
            "taxonAuthor": "(Schmarda, 1859)"
        },
        {
            "taxonLatname": "Notoplana patellarum",
            "taxonAuthor": "(Stimpson, 1855)"
        },
        {
            "taxonLatname": "Leptoplana patellensis",
            "taxonAuthor": "Collingwood, 1876"
        },
        {
            "taxonLatname": "Notoplana ovalis",
            "taxonAuthor": "Bock, 1913"
        }
    ],
    "templateContents": [],
    "genericForms": [],
    "tags": [],
    "seo": {
        "title": null,
        "metaDescription": null
    },
    "externalMedia": [],
    "isFeatured": false
}